my_first_package_project_dio/__init__.py
my_first_package_project_dio/hello_world.py
my_first_package_project_dio/my_name_is.py
my_first_package_project_dio-0.0.1.dist-info/METADATA
my_first_package_project_dio-0.0.1.dist-info/WHEEL
my_first_package_project_dio-0.0.1.dist-info/top_level.txt
my_first_package_project_dio-0.0.1.dist-info/RECORD
